MANIFEST.in
README.rst
setup.cfg
setup.py
docs/HISTORY.txt
src/munin/__init__.py
src/munin.zope.egg-info/PKG-INFO
src/munin.zope.egg-info/SOURCES.txt
src/munin.zope.egg-info/dependency_links.txt
src/munin.zope.egg-info/entry_points.txt
src/munin.zope.egg-info/namespace_packages.txt
src/munin.zope.egg-info/not-zip-safe
src/munin.zope.egg-info/requires.txt
src/munin.zope.egg-info/top_level.txt
src/munin/zope/__init__.py
src/munin/zope/browser.py
src/munin/zope/configure.zcml
src/munin/zope/memory.py
src/munin/zope/plugins.py
src/munin/zope/tests.py
src/munin/zope/tests.zcml