Metadata-Version: 1.0
Name: munin.zope
Version: 2.0
Summary: Munin plugins for Zope/Plone.
Home-page: http://plone.org/products/munin.zope
Author: Andrew Mleczko
Author-email: andrew.mleczko@redturtle.it
License: GPL
Keywords: plone zope munin monitoring
Platform: Any
Classifier: Development Status :: 3 - Alpha
Classifier: Programming Language :: Python
Classifier: Framework :: Plone
Classifier: Framework :: ZODB
Classifier: Framework :: Zope2
Classifier: Intended Audience :: Developers
Classifier: Intended Audience :: System Administrators
Classifier: License :: OSI Approved :: GNU General Public License (GPL)
Classifier: Programming Language :: Python
Classifier: Topic :: System :: Networking :: Monitoring
Classifier: Topic :: Software Development :: Libraries :: Python Modules
